MANIFEST.in
README.md
requirements.txt
setup.py
TaxiFareModel/__init__.py
TaxiFareModel/data.py
TaxiFareModel/encoders.py
TaxiFareModel/trainer.py
TaxiFareModel/utils.py
TaxiFareModel_joacripp.egg-info/PKG-INFO
TaxiFareModel_joacripp.egg-info/SOURCES.txt
TaxiFareModel_joacripp.egg-info/dependency_links.txt
TaxiFareModel_joacripp.egg-info/not-zip-safe
TaxiFareModel_joacripp.egg-info/requires.txt
TaxiFareModel_joacripp.egg-info/top_level.txt
scripts/TaxiFareModel-run
tests/__init__.py